{
    "version": "0.1.32",
    "architecture": {
        "64bit": {
            "url": "https://dl.orionops.tech/cli/releases/v0.1.32/orion-cli_windows_amd64.zip",
            "bin": [
                "orion.exe"
            ],
            "hash": "4a71e9de717dbcd79741ee1fe8e6e01e4f2fe14c10216b37d2a886ec64e66727"
        },
        "arm64": {
            "url": "https://dl.orionops.tech/cli/releases/v0.1.32/orion-cli_windows_arm64.zip",
            "bin": [
                "orion.exe"
            ],
            "hash": "acc3096bddec66e73fe8474c80b4b8570b41e3a726d88bbb187a559b741c4674"
        }
    },
    "homepage": "https://orionops.tech",
    "license": "Proprietary",
    "description": "OrionOps CLI — Specialized AI agents for code generation"
}
