{
    "version": "0.1.16",
    "architecture": {
        "64bit": {
            "url": "https://github.com/Perseusoft/orion-releases/releases/download/v0.1.16/orion-cli_windows_amd64.zip",
            "bin": [
                "orion.exe"
            ],
            "hash": "43db86c3ffddd3ceb4958082a5715ff81bdf67f52364a00ede691041f80e3c30"
        },
        "arm64": {
            "url": "https://github.com/Perseusoft/orion-releases/releases/download/v0.1.16/orion-cli_windows_arm64.zip",
            "bin": [
                "orion.exe"
            ],
            "hash": "a693ec6ae9ea23113ee7492600ee70c7d788fef158be1aff8b6411bc4d5fe2d0"
        }
    },
    "homepage": "https://orionops.tech",
    "license": "Proprietary",
    "description": "OrionOps CLI — Specialized AI agents for code generation"
}
