{
    "version": "0.1.25",
    "architecture": {
        "64bit": {
            "url": "https://dl.orionops.tech/cli/releases/v0.1.25/orion-cli_windows_amd64.zip",
            "bin": [
                "orion.exe"
            ],
            "hash": "03da6d37e7ff21710a8c69a9be91b6ab4b3a67743ffd17d61a872b0ad1f0fd7e"
        },
        "arm64": {
            "url": "https://dl.orionops.tech/cli/releases/v0.1.25/orion-cli_windows_arm64.zip",
            "bin": [
                "orion.exe"
            ],
            "hash": "a05de093cb7641223315a302368cee777593a59db89b0d6e9098f738b3af208c"
        }
    },
    "homepage": "https://orionops.tech",
    "license": "Proprietary",
    "description": "OrionOps CLI — Specialized AI agents for code generation"
}
